MANIFEST.in
README.md
example.py
setup.py
gym_xmoto/__init__.py
gym_xmoto.egg-info/PKG-INFO
gym_xmoto.egg-info/SOURCES.txt
gym_xmoto.egg-info/dependency_links.txt
gym_xmoto.egg-info/requires.txt
gym_xmoto.egg-info/top_level.txt
gym_xmoto/envs/__init__.py
gym_xmoto/envs/capture_score_data.py
gym_xmoto/envs/image_preprocessor.py
gym_xmoto/envs/levels.csv
gym_xmoto/envs/score_recognition.py
gym_xmoto/envs/test_capture_screen.py
gym_xmoto/envs/utils.py
gym_xmoto/envs/xmoto_env.py
gym_xmoto/envs/screenshots/dead.png
gym_xmoto/envs/screenshots/maplines.png
gym_xmoto/envs/screenshots/skip_this_report.png
gym_xmoto/envs/screenshots/win.png